{
  "022f9c89754947ce": "カタログを見る",
  "037c3288fab992b1": "収納家具",
  "04c76b20600a7c27": {
    "c": "注目作品",
    "i": 1,
    "t": "h2"
  },
  "0532c9d9d3d15d09": [
    "これは、国際化機能を紹介するために",
    {
      "c": "General Translation",
      "i": 1,
      "t": "a"
    },
    "で構築されたデモアプリケーションです。実際のストアではありません。"
  ],
  "0582c780e1e0e805": "ダイニングルーム",
  "0638f727aec2a644": "ウォールナット",
  "097b8ce024d02067": "リネンのドラムシェード付きアーチ型真ちゅうフロアランプ。重量のある大理石ベースで安定性を高めています。調光機能付きで、LED対応です。",
  "0e7631abb79c387a": [
    {
      "c": "カート",
      "i": 1,
      "t": "h1"
    },
    {
      "c": "カートは空です。カタログを閲覧して、お気に入りの商品を見つけましょう。",
      "i": 2,
      "t": "p"
    }
  ],
  "111a44209dc6e701": "削除",
  "14e910de6d30773c": "Nara プラットフォームベッド",
  "16d4b1642e8fcaa2": "今まで使った中で一番座り心地のいいチェア。まるでアートピースです。",
  "173d4d98a5d11606": "レザー",
  "18e28258b1b65d2c": "座り心地がとても良く、実物は写真以上に高見えします。リネン生地もとてもきれいです。",
  "19fb6773083d1895": {
    "d": {
      "b": {
        "other": {
          "c": [
            {
              "i": 3,
              "k": "_gt_n_3",
              "v": "n"
            },
            " 点の商品"
          ],
          "i": 2,
          "t": "C2"
        },
        "plural": {
          "c": [
            {
              "i": 3,
              "k": "_gt_n_3",
              "v": "n"
            },
            " 点の商品"
          ],
          "i": 2,
          "t": "C2"
        },
        "singular": {
          "c": [
            {
              "i": 3,
              "k": "_gt_n_3",
              "v": "n"
            },
            " 商品"
          ],
          "i": 2,
          "t": "C2"
        }
      },
      "t": "p"
    },
    "i": 1,
    "t": "Plural"
  },
  "1e889ea7119b4b7c": {
    "c": [
      {
        "i": 2,
        "k": "_gt_n_2",
        "v": "n"
      },
      " 個"
    ],
    "i": 1,
    "t": "p"
  },
  "235998c8a68c6e58": {
    "c": "無料",
    "i": 1,
    "t": "span"
  },
  "23e749f227fab8ee": "Atelier Home",
  "29ebc1b119853fce": "カタログ",
  "2d23e0a0f7f702f3": "Mori ダイニングテーブル",
  "32c4cfc0bc03b4b0": {
    "c": "条件に一致する商品がありません。フィルターを調整してください。",
    "i": 1,
    "t": "p"
  },
  "34a7d2f305897561": "チェア",
  "34b2195b9ad72d79": "レジに進む",
  "3703a0da80c9adde": {
    "c": "最高価格",
    "i": 1,
    "t": "h3"
  },
  "389100854585dfad": "ベッドルーム",
  "3e0077f6480b802f": "本当にお値段以上の価値があります。オーク材フレームの品質は抜群です。",
  "45d3b4589c69111c": "Forma ダイニングチェア",
  "4800094819e49e31": "Oslo 3人掛けソファ",
  "497cc7f4dfd2075b": {
    "c": {
      "d": {
        "b": {
          "backorder": {
            "c": "入荷待ち",
            "i": 3,
            "t": "span"
          },
          "in-stock": {
            "c": "在庫あり",
            "i": 3,
            "t": "span"
          },
          "out-of-stock": {
            "c": "在庫切れ",
            "i": 3,
            "t": "span"
          }
        },
        "t": "b"
      },
      "i": 2,
      "t": "Branch"
    },
    "i": 1,
    "t": "span"
  },
  "49ce78b4d6476b40": {
    "c": "配送地域",
    "i": 1,
    "t": "h3"
  },
  "4a517b2fb2be8d09": "可動棚付きで、前板にアッシュ材のルーバーをあしらったサイドボード。真ちゅう製の取っ手が、明るい木目にあたたかみのあるアクセントを添えます。",
  "4aeebb09c93a1ee0": {
    "c": "カタログ",
    "i": 1,
    "t": "h1"
  },
  "4f94e7beb32bcd47": {
    "c": "合計",
    "i": 1,
    "t": "span"
  },
  "53b34ec196b4f120": "無垢のホワイトオークを使用した5段のオープンシェルフ。非対称な棚の間隔により、さまざまなサイズのオブジェを収納でき、視覚的なアクセントも生まれます。",
  "53bdafb1ece3c13c": {
    "c": [
      {
        "c": "寸法",
        "i": 2,
        "t": "h3"
      },
      {
        "c": {
          "c": [
            {
              "c": [
                {
                  "c": "幅",
                  "i": 6,
                  "t": "td"
                },
                {
                  "c": [
                    {
                      "i": 8,
                      "k": "_gt_n_8",
                      "v": "n"
                    },
                    " cm"
                  ],
                  "i": 7,
                  "t": "td"
                }
              ],
              "i": 5,
              "t": "tr"
            },
            {
              "c": [
                {
                  "c": "奥行き",
                  "i": 10,
                  "t": "td"
                },
                {
                  "c": [
                    {
                      "i": 12,
                      "k": "_gt_n_12",
                      "v": "n"
                    },
                    " cm"
                  ],
                  "i": 11,
                  "t": "td"
                }
              ],
              "i": 9,
              "t": "tr"
            },
            {
              "c": [
                {
                  "c": "高さ",
                  "i": 14,
                  "t": "td"
                },
                {
                  "c": [
                    {
                      "i": 16,
                      "k": "_gt_n_16",
                      "v": "n"
                    },
                    " cm"
                  ],
                  "i": 15,
                  "t": "td"
                }
              ],
              "i": 13,
              "t": "tr"
            },
            {
              "c": [
                {
                  "c": "重量",
                  "i": 18,
                  "t": "td"
                },
                {
                  "c": [
                    {
                      "i": 20,
                      "k": "_gt_n_20",
                      "v": "n"
                    },
                    " kg"
                  ],
                  "i": 19,
                  "t": "td"
                }
              ],
              "i": 17,
              "t": "tr"
            }
          ],
          "i": 4,
          "t": "tbody"
        },
        "i": 3,
        "t": "table"
      }
    ],
    "i": 1,
    "t": "div"
  },
  "5491dd2caa7d78a9": "リビングルーム",
  "54ee9c0e94c24537": "Zen コーヒーテーブル",
  "55639b09575c7a56": {
    "c": {
      "d": {
        "b": {
          "backorder": {
            "c": "入荷待ち — 発送まで2〜4週間",
            "i": 3,
            "t": "span"
          },
          "in-stock": {
            "c": "在庫あり",
            "i": 3,
            "t": "span"
          },
          "out-of-stock": {
            "c": "在庫切れ",
            "i": 3,
            "t": "span"
          }
        },
        "t": "b"
      },
      "i": 2,
      "t": "Branch"
    },
    "i": 1,
    "t": "div"
  },
  "55dcb10dd2ec168b": {
    "c": "カート",
    "i": 1,
    "t": "h1"
  },
  "5767b7ae6e43436d": "ソファ",
  "579b22ac79be1df4": "Koto サイドボード",
  "57b6f38b9a0e95cb": "ソファやコーヒーテーブル、シェルフ、照明を組み合わせて、快適さとすっきりとしたデザインが両立するくつろぎの空間をつくりましょう。",
  "67af7b20a97a488a": "ベッド",
  "6d3aee4c90aebc2a": [
    "配達予定日数：",
    {
      "i": 1,
      "k": "_gt_value_1",
      "v": "v"
    },
    "営業日"
  ],
  "6eb807cd1232e8a8": "カート",
  "72128215322346ae": "デザインが本当に気に入っています。クッションがしっかり体に馴染むまでに数週間かかりました。",
  "74e9c031ab979a01": "テーブル",
  "7550dd8d69eaf310": "上質なデスクと人間工学に基づいたチェア、整理された収納で、集中して創造的に取り組めるワークスペースを整えましょう。",
  "7570b0577ca6e879": "メタル",
  "7ba0fd2bb81d5fe6": "ケーブルマネジメントが本当によくできていて、天板も広くてなめらかです。",
  "7bdd118d7c6a6d00": {
    "c": "注文の概要",
    "i": 1,
    "t": "h2"
  },
  "7c4fe22086e2a0f7": "Luna ナイトテーブル",
  "800c4dcf86606b3e": "すべて表示",
  "830aa72a6f039ab3": {
    "c": "新着情報",
    "i": 1,
    "t": "h2"
  },
  "86e6edb49128a9aa": "クリーム",
  "8a5c9dd92fcb2fc9": "コニャック",
  "91fc99c9c961902f": {
    "c": "カテゴリ",
    "i": 1,
    "t": "h3"
  },
  "92e01740ca5ff89f": {
    "c": "部屋別に探す",
    "i": 1,
    "t": "h2"
  },
  "9761415047e5023f": [
    {
      "c": "厳選コレクション",
      "i": 1,
      "t": "p"
    },
    {
      "c": [
        "丁寧な暮らしのための",
        {
          "i": 3,
          "t": "br"
        },
        "家具"
      ],
      "i": 2,
      "t": "h1"
    },
    {
      "c": "すべての製品は、品質・耐久性・普遍的なデザインを重視し、持続可能な素材で丁寧に作られています。",
      "i": 4,
      "t": "p"
    }
  ],
  "980341ff8f49b488": [
    {
      "i": 1,
      "k": "_gt_n_1",
      "v": "n"
    },
    " / 5"
  ],
  "9b0b8c52f79371d1": {
    "c": "配送",
    "i": 1,
    "t": "span"
  },
  "9f56a31e08495d35": "ナチュラル",
  "9fb81ec03631b1eb": "レザーが驚くほど柔らかく、半年使ったあとの経年変化もとても美しいです。",
  "a4ed7adc9fba07f0": "継ぎ目の仕上がりが見事で、きしみもなく、とてもしっかりしています。ウォルナットの木目も本当に美しいです。",
  "a714f1308dff9b8b": "ライトブラウン",
  "a84c0666f00c0c6b": "真鍮",
  "a89a73bc278a41b0": "美しくてミニマル。まさに探し求めていた美学です。",
  "aa1e35d5c5481567": "アッシュ",
  "ab5063481718352a": "彫刻的な背もたれを持つスタッキング可能なダイニングチェア。スチーム曲げ加工を施したオーク材フレームに、ペーパーコードを編み込んだ座面を組み合わせています。",
  "ab7705d302ac5aae": "リネン類",
  "abd5f7509ccfb3eb": "Vela ラウンジチェア",
  "b0cb68b3da7e1aa3": "無垢材のテーブルに造形的なチェアを合わせて、どんな食事の時間も特別に感じられるダイニングを演出しましょう。",
  "b0fc08b76cb313bc": "木のぬくもりのあるベッドフレームとナイトテーブル、やわらかな間接照明に包まれて、休息とリフレッシュの時間を過ごしましょう。",
  "b3ebdf162810c334": "国内標準配送",
  "b4fb4d1fd6aa5eea": "MUJI モジュラーシェルフ",
  "b5ef6ddd6bb2582e": "アークフロアランプ",
  "b69b6930d664674f": "Aura ライティングデスク",
  "b92385b34d0a19f0": "モダン家具のECサイトを想定したデモとして、General Translation による多言語対応を紹介します。ソファやテーブル、ベッドなど、さまざまなアイテムを閲覧できます。",
  "ba87af213646bec2": "自由に組み替えられるモジュール式シェルフシステム。5段×3列。引き出しや扉を追加することも、オープンのまま使うこともできます。無垢オーク材を二重ほぞ継ぎで仕上げています。",
  "bf78134d06f0d41b": "デスク",
  "c0288285cea7a9ae": "無垢アメリカンウォルナット材を使用した、ロープロファイル設計のプラットフォームベッド。金具を見せない日本風の木組み構造を採用し、すのこベースが付属します。",
  "c340c0536d25e713": [
    "最大 ",
    {
      "i": 1,
      "k": "_gt_n_1",
      "v": "n"
    },
    " USD"
  ],
  "c4e78e2dce9a5f98": {
    "c": "素材",
    "i": 1,
    "t": "h3"
  },
  "c8fc0d87c5f80292": {
    "c": "素材",
    "i": 1,
    "t": "h3"
  },
  "ca13edcb2af07b35": "カートに追加",
  "cc90ecd6915d3d41": [
    {
      "c": "カスタマーレビュー",
      "i": 1,
      "t": "h2"
    },
    {
      "c": [
        {
          "i": 3,
          "k": "_gt_n_3",
          "v": "n"
        },
        "／5 — ",
        {
          "i": 4,
          "k": "_gt_n_4",
          "v": "n"
        },
        "件のレビュー"
      ],
      "i": 2,
      "t": "p"
    }
  ],
  "ccb79809e4318157": "引き出し1杯とオープンシェルフを備えたコンパクトなナイトスタンド。ソフトクローズ機能付きのスライドレールを採用し、Nara Platform Bedとの相性も抜群です。",
  "cda31a9a4b6ea03b": "無垢ホワイトオーク材を使用したダイニングテーブルに、ライブエッジのディテールをあしらいました。木目の表情を引き立てるマットなナチュラルオイルで、一つひとつ手作業で仕上げています。",
  "d3f83eefb0bd2f01": {
    "d": {
      "b": {
        "other": {
          "c": [
            {
              "i": 3,
              "k": "_gt_n_3",
              "v": "n"
            },
            " 件"
          ],
          "i": 2,
          "t": "C2"
        },
        "plural": {
          "c": [
            {
              "i": 3,
              "k": "_gt_n_3",
              "v": "n"
            },
            " 件"
          ],
          "i": 2,
          "t": "C2"
        },
        "singular": {
          "c": [
            {
              "i": 3,
              "k": "_gt_n_3",
              "v": "n"
            },
            " 件"
          ],
          "i": 2,
          "t": "C2"
        }
      },
      "t": "p"
    },
    "i": 1,
    "t": "Plural"
  },
  "d43d8327999de115": "カートを空にする",
  "d531ece6fb8c6908": "Atelier Home Furniture | General Translation",
  "d536892d4c7d0388": {
    "c": "カラー",
    "i": 1,
    "t": "h3"
  },
  "d90ea80804241b55": "地域配送（半径50km以内）",
  "dd4307d70a4178c0": {
    "c": [
      {
        "c": [
          {
            "c": "Atelier Home",
            "i": 3,
            "t": "h3"
          },
          {
            "c": "現代の暮らしに向けた、こだわりのある家具。すべての製品は持続可能な素材から作られており、品質と耐久性を重視しています。",
            "i": 4,
            "t": "p"
          }
        ],
        "i": 2,
        "t": "div"
      },
      {
        "c": [
          {
            "c": "デザインリソース",
            "i": 6,
            "t": "h3"
          },
          {
            "c": [
              {
                "c": {
                  "c": "Herman Miller",
                  "i": 9,
                  "t": "a"
                },
                "i": 8,
                "t": "li"
              },
              {
                "c": {
                  "c": "Design Within Reach",
                  "i": 11,
                  "t": "a"
                },
                "i": 10,
                "t": "li"
              },
              {
                "c": {
                  "c": "Dezeen",
                  "i": 13,
                  "t": "a"
                },
                "i": 12,
                "t": "li"
              },
              {
                "c": {
                  "c": "Architectural Digest",
                  "i": 15,
                  "t": "a"
                },
                "i": 14,
                "t": "li"
              }
            ],
            "i": 7,
            "t": "ul"
          }
        ],
        "i": 5,
        "t": "div"
      },
      {
        "c": [
          {
            "c": "このデモについて",
            "i": 17,
            "t": "h3"
          },
          {
            "c": [
              "これは国際化のデモンストレーションのために ",
              {
                "c": "General Translation",
                "i": 19,
                "t": "a"
              },
              " を使って構築されたサンプルアプリケーションです。実際の店舗やサービスではありません。"
            ],
            "i": 18,
            "t": "p"
          }
        ],
        "i": 16,
        "t": "div"
      }
    ],
    "i": 1,
    "t": "div"
  },
  "de2dbe5fab61d0c3": {
    "c": "小計",
    "i": 1,
    "t": "span"
  },
  "df7ea979d6a46f87": "Haven ブックシェルフ",
  "e0dbf8ea9af44393": "オフィス",
  "e1e568362f95d224": "仕上げの職人技が素晴らしく、自然オイル仕上げの手触りもとても良いです。",
  "e58e7404a2f11bff": "照明",
  "e619ac3f4de61fb1": {
    "c": "上のお部屋を選択すると、そのスペースに合わせた家具をご覧いただけます。",
    "i": 1,
    "t": "p"
  },
  "e71d68e634b67769": "丸みのある縁と下段棚を備えたオーバル型コーヒーテーブル。無垢のオーク材を使用し、手作業でオイル仕上げを施しています。",
  "e7c0553f70c9ca10": "国際配送",
  "e8caefaf4ee4081c": "すっきりしたラインに、ゆったりとしたサイズ感のソファです。無垢オーク材のフレームに高反発クッションを組み合わせ、上質なヨーロッパ産リネンで包んでいます。",
  "ec8880884cbcda48": "ダークブラウン",
  "ee0bb8f51c03153b": "オーク材",
  "f15a46fd65bc6906": "部屋",
  "f307a83d2240a0c6": {
    "c": "この商品のレビューはまだありません。",
    "i": 1,
    "t": "p"
  },
  "f6119f523c93b780": "ライブエッジのディテールが本当に見事で、ダイニングルームの主役になっています。",
  "f78c6bdd9349aa9c": "国内速達便",
  "f7da08ed1cad34f7": "ヨーロピアンアッシュ材を使用したミニマルなライティングデスク。引き出し1杯と一体型の配線収納を備え、先細りの脚先には真鍮キャップがあしらわれています。",
  "fb7aebfeb22fd513": "フルグレインイタリアンレザー張りのラウンジチェア。成形合板のシェル構造で、レザーは使い込むほどに味わいのある美しい艶が増していきます。"
}